odoo10_addon_website_portal_contract-10.0.1.0.0-py2.7-nspkg.pth
odoo/addons/website_portal_contract/README.rst
odoo/addons/website_portal_contract/__init__.py
odoo/addons/website_portal_contract/__manifest__.py
odoo/addons/website_portal_contract/controllers/__init__.py
odoo/addons/website_portal_contract/controllers/main.py
odoo/addons/website_portal_contract/data/website_contract_template_data.xml
odoo/addons/website_portal_contract/demo/account_analytic_account_demo.xml
odoo/addons/website_portal_contract/demo/account_analytic_contract_demo.xml
odoo/addons/website_portal_contract/demo/account_analytic_invoice_line_demo.xml
odoo/addons/website_portal_contract/demo/assets_demo.xml
odoo/addons/website_portal_contract/models/__init__.py
odoo/addons/website_portal_contract/models/account_analytic_account.py
odoo/addons/website_portal_contract/models/account_analytic_contract.py
odoo/addons/website_portal_contract/models/account_analytic_contract_template.py
odoo/addons/website_portal_contract/security/ir.model.access.csv
odoo/addons/website_portal_contract/static/description/icon.png
odoo/addons/website_portal_contract/static/src/js/tour_test_contract.js
odoo/addons/website_portal_contract/tests/__init__.py
odoo/addons/website_portal_contract/tests/test_account_analytic_account.py
odoo/addons/website_portal_contract/tests/test_account_analytic_contract.py
odoo/addons/website_portal_contract/tests/test_account_analytic_contract_template.py
odoo/addons/website_portal_contract/tests/test_controller.py
odoo/addons/website_portal_contract/views/account_analytic_account_view.xml
odoo/addons/website_portal_contract/views/account_analytic_contract_template_view.xml
odoo/addons/website_portal_contract/views/account_analytic_contract_view.xml
odoo/addons/website_portal_contract/views/website_portal_contract_templates.xml
odoo10_addon_website_portal_contract-10.0.1.0.0.dist-info/DESCRIPTION.rst
odoo10_addon_website_portal_contract-10.0.1.0.0.dist-info/METADATA
odoo10_addon_website_portal_contract-10.0.1.0.0.dist-info/RECORD
odoo10_addon_website_portal_contract-10.0.1.0.0.dist-info/WHEEL
odoo10_addon_website_portal_contract-10.0.1.0.0.dist-info/metadata.json
odoo10_addon_website_portal_contract-10.0.1.0.0.dist-info/namespace_packages.txt
odoo10_addon_website_portal_contract-10.0.1.0.0.dist-info/top_level.txt
